{"CONCEPT_ID":[4021336],"CDM_TABLE_NAME":["CONDITION_OCCURRENCE"],"CONCEPT_NAME":["At risk for suicide"],"NUM_PERSONS":[1],"PERCENT_PERSONS":["0.0006"],"RECORDS_PER_PERSON":["1.0"],"PREVALENCE_BY_GENDER_AGE_YEAR":[{"TRELLIS_NAME":"20-29","SERIES_NAME":"MALE","X_CALENDAR_YEAR":2002,"Y_PREVALENCE_1000PP":14.4927}],"PREVALENCE_BY_MONTH":[{"X_CALENDAR_MONTH":200208,"Y_PREVALENCE_1000PP":1.0341}],"CONDITIONS_BY_TYPE":[{"CONCEPT_NAME":"Prescription dispensed in pharmacy","COUNT_VALUE":1}],"AGE_AT_FIRST_DIAGNOSIS":[{"CATEGORY":"MALE","MIN_VALUE":25,"P10_VALUE":25,"P25_VALUE":25,"MEDIAN_VALUE":25,"P75_VALUE":25,"P90_VALUE":25,"MAX_VALUE":25}]}
