{"CONCEPT_ID":[4094814],"CDM_TABLE_NAME":["CONDITION_OCCURRENCE"],"CONCEPT_NAME":["Bullet wound"],"NUM_PERSONS":[18],"PERCENT_PERSONS":["0.0102"],"RECORDS_PER_PERSON":["1.1"],"PREVALENCE_BY_GENDER_AGE_YEAR":[{"TRELLIS_NAME":"-30--21","SERIES_NAME":"MALE","X_CALENDAR_YEAR":1957,"Y_PREVALENCE_1000PP":166.6667},{"TRELLIS_NAME":"10-19","SERIES_NAME":"MALE","X_CALENDAR_YEAR":1957,"Y_PREVALENCE_1000PP":41.6667},{"TRELLIS_NAME":"20-29","SERIES_NAME":"FEMALE","X_CALENDAR_YEAR":1960,"Y_PREVALENCE_1000PP":52.6316},{"TRELLIS_NAME":"0-9","SERIES_NAME":"FEMALE","X_CALENDAR_YEAR":1961,"Y_PREVALENCE_1000PP":47.6191},{"TRELLIS_NAME":"10-19","SERIES_NAME":"MALE","X_CALENDAR_YEAR":1975,"Y_PREVALENCE_1000PP":20},{"TRELLIS_NAME":"40-49","SERIES_NAME":"MALE","X_CALENDAR_YEAR":1975,"Y_PREVALENCE_1000PP":100},{"TRELLIS_NAME":"20-29","SERIES_NAME":"FEMALE","X_CALENDAR_YEAR":1979,"Y_PREVALENCE_1000PP":13.3333},{"TRELLIS_NAME":"0-9","SERIES_NAME":"MALE","X_CALENDAR_YEAR":1980,"Y_PREVALENCE_1000PP":45.4545},{"TRELLIS_NAME":"20-29","SERIES_NAME":"FEMALE","X_CALENDAR_YEAR":1998,"Y_PREVALENCE_1000PP":12.8205},{"TRELLIS_NAME":"20-29","SERIES_NAME":"MALE","X_CALENDAR_YEAR":2006,"Y_PREVALENCE_1000PP":13.3333},{"TRELLIS_NAME":"70-79","SERIES_NAME":"FEMALE","X_CALENDAR_YEAR":2008,"Y_PREVALENCE_1000PP":43.4783},{"TRELLIS_NAME":"20-29","SERIES_NAME":"MALE","X_CALENDAR_YEAR":2011,"Y_PREVALENCE_1000PP":10.2041},{"TRELLIS_NAME":"10-19","SERIES_NAME":"FEMALE","X_CALENDAR_YEAR":2011,"Y_PREVALENCE_1000PP":7.8125},{"TRELLIS_NAME":"70-79","SERIES_NAME":"MALE","X_CALENDAR_YEAR":2013,"Y_PREVALENCE_1000PP":33.3333},{"TRELLIS_NAME":"30-39","SERIES_NAME":"FEMALE","X_CALENDAR_YEAR":2013,"Y_PREVALENCE_1000PP":10.101},{"TRELLIS_NAME":"0-9","SERIES_NAME":"MALE","X_CALENDAR_YEAR":2014,"Y_PREVALENCE_1000PP":11.6279},{"TRELLIS_NAME":"10-19","SERIES_NAME":"MALE","X_CALENDAR_YEAR":2014,"Y_PREVALENCE_1000PP":8},{"TRELLIS_NAME":"10-19","SERIES_NAME":"MALE","X_CALENDAR_YEAR":2016,"Y_PREVALENCE_1000PP":9.2593},{"TRELLIS_NAME":"20-29","SERIES_NAME":"MALE","X_CALENDAR_YEAR":2016,"Y_PREVALENCE_1000PP":7.4074},{"TRELLIS_NAME":"10-19","SERIES_NAME":"MALE","X_CALENDAR_YEAR":2020,"Y_PREVALENCE_1000PP":10.4167},{"TRELLIS_NAME":"20-29","SERIES_NAME":"MALE","X_CALENDAR_YEAR":2021,"Y_PREVALENCE_1000PP":34.4828}],"PREVALENCE_BY_MONTH":[{"X_CALENDAR_MONTH":195711,"Y_PREVALENCE_1000PP":5},{"X_CALENDAR_MONTH":196011,"Y_PREVALENCE_1000PP":4.1322},{"X_CALENDAR_MONTH":196101,"Y_PREVALENCE_1000PP":4.1152},{"X_CALENDAR_MONTH":197510,"Y_PREVALENCE_1000PP":2.1598},{"X_CALENDAR_MONTH":197901,"Y_PREVALENCE_1000PP":1.9048},{"X_CALENDAR_MONTH":198010,"Y_PREVALENCE_1000PP":1.8116},{"X_CALENDAR_MONTH":199808,"Y_PREVALENCE_1000PP":1.1038},{"X_CALENDAR_MONTH":200612,"Y_PREVALENCE_1000PP":0.9515},{"X_CALENDAR_MONTH":200808,"Y_PREVALENCE_1000PP":0.9276},{"X_CALENDAR_MONTH":201103,"Y_PREVALENCE_1000PP":0.823},{"X_CALENDAR_MONTH":201110,"Y_PREVALENCE_1000PP":0.7092},{"X_CALENDAR_MONTH":201311,"Y_PREVALENCE_1000PP":0.6627},{"X_CALENDAR_MONTH":201408,"Y_PREVALENCE_1000PP":1.3175},{"X_CALENDAR_MONTH":201603,"Y_PREVALENCE_1000PP":0.6536},{"X_CALENDAR_MONTH":201610,"Y_PREVALENCE_1000PP":0.6549},{"X_CALENDAR_MONTH":202011,"Y_PREVALENCE_1000PP":1.2788},{"X_CALENDAR_MONTH":202101,"Y_PREVALENCE_1000PP":1.9841}],"CONDITIONS_BY_TYPE":[{"CONCEPT_NAME":"Prescription dispensed in pharmacy","COUNT_VALUE":19}],"AGE_AT_FIRST_DIAGNOSIS":[{"CATEGORY":"MALE","MIN_VALUE":-24,"P10_VALUE":3,"P25_VALUE":11,"MEDIAN_VALUE":16,"P75_VALUE":27,"P90_VALUE":46,"MAX_VALUE":77},{"CATEGORY":"FEMALE","MIN_VALUE":4,"P10_VALUE":4,"P25_VALUE":12,"MEDIAN_VALUE":26,"P75_VALUE":36,"P90_VALUE":78,"MAX_VALUE":78}]}
